isobuilder/__init__.py
isobuilder/cli.py
isobuilder/constants.py
isobuilder-0.8.0.dist-info/LICENCE
isobuilder-0.8.0.dist-info/METADATA
isobuilder-0.8.0.dist-info/WHEEL
isobuilder-0.8.0.dist-info/entry_points.txt
isobuilder-0.8.0.dist-info/top_level.txt
isobuilder-0.8.0.dist-info/RECORD
