Metadata-Version: 2.1
Name: isobuilder
Version: 0.8.0
Summary: This is a tool for building custom ISO images used for IMRS
Author-email: John Bond <john.bond@icann.org>
Requires-Python: >=3.6
License-File: LICENCE
Requires-Dist: dataclasses
Requires-Dist: passlib
Requires-Dist: PyYAML
